{
  "kind": "collectionType",
  "collectionName": "colors",
  "info": {
    "singularName": "color",
    "pluralName": "colors",
    "displayName": "Color",
    "description": ""
  },
  "options": {
    "draftAndPublish": false
  },
  "pluginOptions": {},
  "attributes": {
    "title": {
      "type": "string",
      "required": true,
      "unique": true
    },
    "status": {
      "type": "boolean",
      "default": false,
      "required": true
    },
    "product": {
      "type": "relation",
      "relation": "manyToOne",
      "target": "api::product.product",
      "inversedBy": "colors"
    },
    "image": {
      "type": "relation",
      "relation": "oneToOne",
      "target": "api::image.image",
      "mappedBy": "color"
    }
  }
}
